{
  "fields": [
    {
      "protocols": {
        "required": true,
        "default": [
          "grpc",
          "grpcs",
          "http",
          "https"
        ],
        "description": "A set of strings representing protocols.",
        "type": "set",
        "elements": {
          "description": "A string representing a protocol, such as HTTP or HTTPS.",
          "type": "string",
          "one_of": [
            "grpc",
            "grpcs",
            "http",
            "https",
            "tcp",
            "tls",
            "tls_passthrough",
            "udp",
            "ws",
            "wss"
          ]
        }
      }
    },
    {
      "config": {
        "fields": [
          {
            "http_method": {
              "description": "A string representing an HTTP method, such as GET, POST, PUT, or DELETE. The string must contain only uppercase letters.",
              "type": "string",
              "match": "^%u+$"
            }
          },
          {
            "remove": {
              "fields": [
                {
                  "body": {
                    "default": [

                    ],
                    "required": true,
                    "type": "array",
                    "elements": {
                      "type": "string"
                    }
                  }
                },
                {
                  "headers": {
                    "default": [

                    ],
                    "required": true,
                    "type": "array",
                    "elements": {
                      "type": "string"
                    }
                  }
                },
                {
                  "querystring": {
                    "default": [

                    ],
                    "required": true,
                    "type": "array",
                    "elements": {
                      "type": "string"
                    }
                  }
                }
              ],
              "type": "record",
              "required": true
            }
          },
          {
            "rename": {
              "fields": [
                {
                  "body": {
                    "default": [

                    ],
                    "required": true,
                    "type": "array",
                    "elements": {
                      "type": "string"
                    }
                  }
                },
                {
                  "headers": {
                    "default": [

                    ],
                    "required": true,
                    "type": "array",
                    "elements": {
                      "type": "string",
                      "match": "^[^:]+:.*$"
                    }
                  }
                },
                {
                  "querystring": {
                    "default": [

                    ],
                    "required": true,
                    "type": "array",
                    "elements": {
                      "type": "string"
                    }
                  }
                }
              ],
              "type": "record",
              "required": true
            }
          },
          {
            "replace": {
              "fields": [
                {
                  "body": {
                    "default": [

                    ],
                    "required": true,
                    "type": "array",
                    "elements": {
                      "type": "string"
                    }
                  }
                },
                {
                  "headers": {
                    "default": [

                    ],
                    "required": true,
                    "type": "array",
                    "elements": {
                      "type": "string",
                      "match": "^[^:]+:.*$"
                    }
                  }
                },
                {
                  "querystring": {
                    "default": [

                    ],
                    "required": true,
                    "type": "array",
                    "elements": {
                      "type": "string"
                    }
                  }
                },
                {
                  "uri": {
                    "type": "string"
                  }
                }
              ],
              "type": "record",
              "required": true
            }
          },
          {
            "add": {
              "fields": [
                {
                  "body": {
                    "default": [

                    ],
                    "required": true,
                    "type": "array",
                    "elements": {
                      "type": "string"
                    }
                  }
                },
                {
                  "headers": {
                    "default": [

                    ],
                    "required": true,
                    "type": "array",
                    "elements": {
                      "type": "string",
                      "match": "^[^:]+:.*$"
                    }
                  }
                },
                {
                  "querystring": {
                    "default": [

                    ],
                    "required": true,
                    "type": "array",
                    "elements": {
                      "type": "string"
                    }
                  }
                }
              ],
              "type": "record",
              "required": true
            }
          },
          {
            "append": {
              "fields": [
                {
                  "body": {
                    "default": [

                    ],
                    "required": true,
                    "type": "array",
                    "elements": {
                      "type": "string"
                    }
                  }
                },
                {
                  "headers": {
                    "default": [

                    ],
                    "required": true,
                    "type": "array",
                    "elements": {
                      "type": "string",
                      "match": "^[^:]+:.*$"
                    }
                  }
                },
                {
                  "querystring": {
                    "default": [

                    ],
                    "required": true,
                    "type": "array",
                    "elements": {
                      "type": "string"
                    }
                  }
                }
              ],
              "type": "record",
              "required": true
            }
          }
        ],
        "type": "record",
        "required": true
      }
    }
  ],
  "entity_checks": [

  ]
}