{
  "fields": [
    {
      "protocols": {
        "required": true,
        "description": "A set of strings representing HTTP protocols.",
        "elements": {
          "one_of": [
            "grpc",
            "grpcs",
            "http",
            "https"
          ],
          "type": "string"
        },
        "default": [
          "grpc",
          "grpcs",
          "http",
          "https"
        ],
        "type": "set"
      }
    },
    {
      "config": {
        "required": true,
        "fields": [
          {
            "host": {
              "default": "localhost",
              "required": true,
              "description": "The host of the sanitizer",
              "type": "string"
            }
          },
          {
            "port": {
              "default": 8080,
              "required": true,
              "description": "The port of the sanitizer",
              "type": "number"
            }
          },
          {
            "scheme": {
              "default": "http",
              "required": true,
              "description": "The protocol can be http and https",
              "type": "string"
            }
          },
          {
            "timeout": {
              "default": 10000,
              "description": "Connection timeout with the sanitizer",
              "type": "number"
            }
          },
          {
            "keepalive_timeout": {
              "default": 60000,
              "description": "The keepalive timeout for the established http connnection",
              "type": "number"
            }
          },
          {
            "stop_on_error": {
              "default": true,
              "description": "Stop processing if an error occurs",
              "type": "boolean"
            }
          },
          {
            "anonymize": {
              "required": true,
              "description": "List of types to be anonymized",
              "type": "array",
              "default": [
                "all_and_credentials"
              ],
              "elements": {
                "one_of": [
                  "general",
                  "phone",
                  "email",
                  "creditcard",
                  "crypto",
                  "date",
                  "ssn",
                  "ip",
                  "nrp",
                  "domain",
                  "credentials",
                  "url",
                  "medical",
                  "driverlicense",
                  "passport",
                  "bank",
                  "nationalid",
                  "custom",
                  "all",
                  "all_and_credentials"
                ],
                "type": "string"
              }
            }
          },
          {
            "recover_redacted": {
              "default": true,
              "description": "Whether to recover redacted data",
              "type": "boolean"
            }
          },
          {
            "redact_type": {
              "one_of": [
                "placeholder",
                "synthetic"
              ],
              "default": "placeholder",
              "description": "What value to be used to redacted to",
              "type": "string"
            }
          },
          {
            "custom_patterns": {
              "required": false,
              "description": "List of custom patterns to be used for anonymization",
              "len_min": 1,
              "type": "array",
              "elements": {
                "fields": [
                  {
                    "name": {
                      "type": "string",
                      "required": true
                    }
                  },
                  {
                    "regex": {
                      "type": "string",
                      "required": true
                    }
                  },
                  {
                    "score": {
                      "between": [
                        0,
                        1
                      ],
                      "required": true,
                      "default": 0.5,
                      "type": "number"
                    }
                  }
                ],
                "type": "record"
              }
            }
          }
        ],
        "type": "record"
      }
    }
  ],
  "entity_checks": [
    {
      "custom_entity_check": {
        "field_sources": [
          "config"
        ]
      }
    }
  ]
}