{
  "entity_checks": [],
  "fields": [
    {
      "protocols": {
        "type": "set",
        "required": true,
        "description": "A set of strings representing HTTP protocols.",
        "default": [
          "grpc",
          "grpcs",
          "http",
          "https"
        ],
        "elements": {
          "type": "string",
          "one_of": [
            "grpc",
            "grpcs",
            "http",
            "https"
          ]
        }
      }
    },
    {
      "config": {
        "type": "record",
        "fields": [
          {
            "remove": {
              "type": "record",
              "fields": [
                {
                  "json": {
                    "type": "array",
                    "default": [],
                    "elements": {
                      "type": "string"
                    }
                  }
                },
                {
                  "headers": {
                    "type": "array",
                    "default": [],
                    "elements": {
                      "type": "string"
                    }
                  }
                },
                {
                  "if_status": {
                    "type": "array",
                    "default": [],
                    "elements": {
                      "type": "string"
                    }
                  }
                }
              ],
              "required": true
            }
          },
          {
            "rename": {
              "type": "record",
              "fields": [
                {
                  "headers": {
                    "type": "array",
                    "default": [],
                    "elements": {
                      "type": "string",
                      "match": "^[^:]+:.*$"
                    }
                  }
                },
                {
                  "if_status": {
                    "type": "array",
                    "default": [],
                    "elements": {
                      "type": "string"
                    }
                  }
                }
              ],
              "required": true
            }
          },
          {
            "replace": {
              "type": "record",
              "fields": [
                {
                  "body": {
                    "description": "String with which to replace the entire response body.",
                    "type": "string"
                  }
                },
                {
                  "json": {
                    "type": "array",
                    "default": [],
                    "elements": {
                      "type": "string"
                    }
                  }
                },
                {
                  "json_types": {
                    "type": "array",
                    "default": [],
                    "elements": {
                      "type": "string",
                      "one_of": [
                        "boolean",
                        "number",
                        "string"
                      ]
                    }
                  }
                },
                {
                  "headers": {
                    "type": "array",
                    "default": [],
                    "elements": {
                      "type": "string"
                    }
                  }
                },
                {
                  "if_status": {
                    "type": "array",
                    "default": [],
                    "elements": {
                      "type": "string"
                    }
                  }
                }
              ],
              "required": true
            }
          },
          {
            "add": {
              "type": "record",
              "fields": [
                {
                  "json": {
                    "type": "array",
                    "default": [],
                    "elements": {
                      "type": "string"
                    }
                  }
                },
                {
                  "json_types": {
                    "type": "array",
                    "default": [],
                    "elements": {
                      "type": "string",
                      "one_of": [
                        "boolean",
                        "number",
                        "string"
                      ]
                    }
                  }
                },
                {
                  "headers": {
                    "type": "array",
                    "default": [],
                    "elements": {
                      "type": "string"
                    }
                  }
                },
                {
                  "if_status": {
                    "type": "array",
                    "default": [],
                    "elements": {
                      "type": "string"
                    }
                  }
                }
              ],
              "required": true
            }
          },
          {
            "append": {
              "type": "record",
              "fields": [
                {
                  "json": {
                    "type": "array",
                    "default": [],
                    "elements": {
                      "type": "string"
                    }
                  }
                },
                {
                  "json_types": {
                    "type": "array",
                    "default": [],
                    "elements": {
                      "type": "string",
                      "one_of": [
                        "boolean",
                        "number",
                        "string"
                      ]
                    }
                  }
                },
                {
                  "headers": {
                    "type": "array",
                    "default": [],
                    "elements": {
                      "type": "string"
                    }
                  }
                },
                {
                  "if_status": {
                    "type": "array",
                    "default": [],
                    "elements": {
                      "type": "string"
                    }
                  }
                }
              ],
              "required": true
            }
          },
          {
            "allow": {
              "type": "record",
              "fields": [
                {
                  "json": {
                    "type": "set",
                    "elements": {
                      "type": "string"
                    }
                  }
                }
              ],
              "required": true
            }
          },
          {
            "transform": {
              "type": "record",
              "fields": [
                {
                  "functions": {
                    "type": "array",
                    "default": [],
                    "elements": {
                      "type": "string"
                    }
                  }
                },
                {
                  "if_status": {
                    "type": "array",
                    "default": [],
                    "elements": {
                      "type": "string"
                    }
                  }
                },
                {
                  "json": {
                    "type": "array",
                    "default": [],
                    "elements": {
                      "type": "string"
                    }
                  }
                }
              ],
              "required": true
            }
          },
          {
            "dots_in_keys": {
              "type": "boolean",
              "default": true,
              "description": "Whether dots (for example, `customers.info.phone`) should be treated as part of a property name or used to descend into nested JSON objects.."
            }
          }
        ],
        "required": true
      }
    }
  ]
}